djdownloader/__init__.py
djdownloader/tests.py
djdownloader-0.0.1.dist-info/licenses/LICENSE
djdownloader-0.0.1.dist-info/METADATA
djdownloader-0.0.1.dist-info/WHEEL
djdownloader-0.0.1.dist-info/top_level.txt
djdownloader-0.0.1.dist-info/RECORD
