Metadata-Version: 2.4
Name: djdownloader
Version: 0.0.1
Summary: DjDownloader: Django Download Worker
Author-email: Eugene Rabtsau <e.ryabtsev@gmail.com>
Project-URL: Source, https://github.com/ryabtsev/djdownloader
Classifier: Programming Language :: Python :: 3
Classifier: License :: OSI Approved :: BSD License
Classifier: Operating System :: OS Independent
Requires-Python: >=3.8
License-File: LICENSE
Requires-Dist: Django
Dynamic: license-file
